data_transformations/__init__.py
data_transformations/cross_correlation_function.py
data_transformations/pypirc
data_transformations/time_series_windowing_function.py
data_transformations/transformations.py
data_transformations/transpose_function.py
data_transformations-0.1.0.dist-info/METADATA
data_transformations-0.1.0.dist-info/WHEEL
data_transformations-0.1.0.dist-info/RECORD
