Metadata-Version: 2.1
Name: data-transformations
Version: 0.1.0
Summary: A Python library for common data transformations used in machine learning.
Author: Your Name
Author-email: your.email@example.com
Requires-Python: >=3.8,<4.0
Classifier: Programming Language :: Python :: 3
Classifier: Programming Language :: Python :: 3.8
Classifier: Programming Language :: Python :: 3.9
Classifier: Programming Language :: Python :: 3.10
Classifier: Programming Language :: Python :: 3.11
Classifier: Programming Language :: Python :: 3.12
Requires-Dist: numpy (>=1.20.0,<2.0.0)
